foss42/__init__.py
foss42/version.py
foss42/data/__init__.py
foss42/data/geo/__init__.py
foss42/data/geo/country.py
foss42/geo/__init__.py
foss42/geo/country.py
foss42/helpers/__init__.py
foss42/helpers/geo/__init__.py
foss42/helpers/geo/country.py
foss42/helpers/text/__init__.py
foss42/helpers/text/char.py
foss42/helpers/text/english.py
foss42/helpers/text/humanize.py
foss42/text/__init__.py
foss42/text/convert.py
foss42/text/humanize.py
foss42/text/slugify.py
foss42/text/translate.py
foss42-0.0.2.dist-info/LICENSE
foss42-0.0.2.dist-info/METADATA
foss42-0.0.2.dist-info/WHEEL
foss42-0.0.2.dist-info/top_level.txt
foss42-0.0.2.dist-info/RECORD
