Metadata-Version: 2.1
Name: foss42
Version: 0.0.2
Summary: Core Python library used by foss42 Open Source APIs.
Home-page: https://github.com/foss42/foss42
Author: foss42
Author-email: foss42.org@gmail.com
Project-URL: Homepage, https://foss42.com
Project-URL: Source Code, https://github.com/foss42/foss42-core
Project-URL: Bug Tracker, https://github.com/foss42/foss42-core/issues
Project-URL: Documentation, https://foss42.com
Keywords: foss42 utility coversion validation generate transform ml bi visualization charts language graphs data map
Classifier: Programming Language :: Python :: 3 :: Only
Classifier: Programming Language :: Python :: 3
Classifier: Programming Language :: Python :: 3.10
Classifier: Programming Language :: Python :: 3.11
Classifier: Natural Language :: English
Requires-Python: >=3.10
License-File: LICENSE
Requires-Dist: Unidecode
Requires-Dist: titlecase
Requires-Dist: typeguard
